odoo/addons/github_connector_odoo/README.rst
odoo/addons/github_connector_odoo/__init__.py
odoo/addons/github_connector_odoo/__manifest__.py
odoo/addons/github_connector_odoo/data/function.xml
odoo/addons/github_connector_odoo/data/ir_cron.xml
odoo/addons/github_connector_odoo/data/oca.png
odoo/addons/github_connector_odoo/data/odoo_category_data.xml
odoo/addons/github_connector_odoo/data/odoo_licence.xml
odoo/addons/github_connector_odoo/demo/github_organization.xml
odoo/addons/github_connector_odoo/demo/odoo_author_demo.xml
odoo/addons/github_connector_odoo/demo/odoo_module_demo.xml
odoo/addons/github_connector_odoo/demo/odoo_module_post_demo.xml
odoo/addons/github_connector_odoo/models/__init__.py
odoo/addons/github_connector_odoo/models/github_organization.py
odoo/addons/github_connector_odoo/models/github_repository.py
odoo/addons/github_connector_odoo/models/github_repository_branch.py
odoo/addons/github_connector_odoo/models/odoo_author.py
odoo/addons/github_connector_odoo/models/odoo_category.py
odoo/addons/github_connector_odoo/models/odoo_lib_bin.py
odoo/addons/github_connector_odoo/models/odoo_lib_python.py
odoo/addons/github_connector_odoo/models/odoo_license.py
odoo/addons/github_connector_odoo/models/odoo_module.py
odoo/addons/github_connector_odoo/models/odoo_module_version.py
odoo/addons/github_connector_odoo/readme/CONFIGURE.rst
odoo/addons/github_connector_odoo/readme/CONTRIBUTORS.rst
odoo/addons/github_connector_odoo/readme/DESCRIPTION.rst
odoo/addons/github_connector_odoo/readme/ROADMAP.rst
odoo/addons/github_connector_odoo/readme/USAGE.rst
odoo/addons/github_connector_odoo/security/ir.model.access.csv
odoo/addons/github_connector_odoo/static/description/github_organization_form.png
odoo/addons/github_connector_odoo/static/description/icon.png
odoo/addons/github_connector_odoo/static/description/index.html
odoo/addons/github_connector_odoo/static/description/menu.png
odoo/addons/github_connector_odoo/static/description/odoo_author.png
odoo12_addon_github_connector_odoo-12.0.1.2.0.dist-info/METADATA
odoo12_addon_github_connector_odoo-12.0.1.2.0.dist-info/WHEEL
odoo12_addon_github_connector_odoo-12.0.1.2.0.dist-info/top_level.txt
odoo12_addon_github_connector_odoo-12.0.1.2.0.dist-info/RECORD
