Metadata-Version: 2.1
Name: odoo12-addon-github-connector-odoo
Version: 12.0.1.2.0
Summary: Analyze Odoo modules information from Github repositories
Home-page: UNKNOWN
Author: Odoo Community Association (OCA), Sylvain LE GAL, GRAP
Author-email: support@odoo-community.org
License: AGPL-3
Platform: UNKNOWN
Classifier: Programming Language :: Python
Classifier: Framework :: Odoo
Classifier: License :: OSI Approved :: GNU Affero General Public License v3
Requires-Python: >=3.5
Requires-Dist: odoo12-addon-github-connector
Requires-Dist: odoo (<12.1dev,>=12.0a)
